ShiftingBloomFilter/__init__.py
ShiftingBloomFilter/exceptions.py
ShiftingBloomFilter/shifting_bloom_filter.py
ShiftingBloomFilter/utils.py
ShiftingBloomFilter-1.0.dist-info/LICENSE
ShiftingBloomFilter-1.0.dist-info/METADATA
ShiftingBloomFilter-1.0.dist-info/WHEEL
ShiftingBloomFilter-1.0.dist-info/top_level.txt
ShiftingBloomFilter-1.0.dist-info/RECORD
