Metadata-Version: 2.1
Name: ShiftingBloomFilter
Version: 1.0
Summary: Implemenation of shifting bloom filter in python 3
Author-email: hero24 <hero24@interia.pl>
Project-URL: Homepage, https://github.com/hero24/ShiftingBloomFilter
Project-URL: Issues, https://github.com/hero24/ShiftingBloomFilter/issues/
Classifier: Programming Language :: Python :: 3
Classifier: License :: OSI Approved :: GNU General Public License v3 or later (GPLv3+)
Classifier: Operating System :: OS Independent
Requires-Python: >3.0
License-File: LICENSE
